gm-3.0.180.data/purelib/gm-3.0.180-py3.11-nspkg.pth
gm-3.0.180.data/purelib/gm/__version__.py
gm-3.0.180.data/purelib/gm/callback.py
gm-3.0.180.data/purelib/gm/constant.py
gm-3.0.180.data/purelib/gm/enum.py
gm-3.0.180.data/purelib/gm/pb_to_dict.py
gm-3.0.180.data/purelib/gm/util.py
gm-3.0.180.data/purelib/gm/utils.py
gm-3.0.180.data/purelib/gm/_calc/__init__.py
gm-3.0.180.data/purelib/gm/_calc/binomial.py
gm-3.0.180.data/purelib/gm/_calc/black76.py
gm-3.0.180.data/purelib/gm/_calc/black_scholes.py
gm-3.0.180.data/purelib/gm/api/__init__.py
gm-3.0.180.data/purelib/gm/api/_errors.py
gm-3.0.180.data/purelib/gm/api/_utils.py
gm-3.0.180.data/purelib/gm/api/basic.py
gm-3.0.180.data/purelib/gm/api/bond.py
gm-3.0.180.data/purelib/gm/api/calc.py
gm-3.0.180.data/purelib/gm/api/credit.py
gm-3.0.180.data/purelib/gm/api/ds_fund.py
gm-3.0.180.data/purelib/gm/api/ds_instrument.py
gm-3.0.180.data/purelib/gm/api/errors.py
gm-3.0.180.data/purelib/gm/api/fund.py
gm-3.0.180.data/purelib/gm/api/ipo.py
gm-3.0.180.data/purelib/gm/api/query.py
gm-3.0.180.data/purelib/gm/api/trade.py
gm-3.0.180.data/purelib/gm/api/trade_option.py
gm-3.0.180.data/purelib/gm/csdk/__init__.py
gm-3.0.180.data/purelib/gm/csdk/c_sdk.cp311-win_amd64.pyd
gm-3.0.180.data/purelib/gm/csdk/c_sdk.pyi
gm-3.0.180.data/purelib/gm/csdk/gmpytool.pyd
gm-3.0.180.data/purelib/gm/csdk/gmsdk.dll
gm-3.0.180.data/purelib/gm/csdk/setup.py
gm-3.0.180.data/purelib/gm/csdk/setup_linux.py
gm-3.0.180.data/purelib/gm/csdk/thostmd_wrap.dll
gm-3.0.180.data/purelib/gm/csdk/thostmduserapi_se.dll
gm-3.0.180.data/purelib/gm/model/__init__.py
gm-3.0.180.data/purelib/gm/model/account.py
gm-3.0.180.data/purelib/gm/model/storage.py
gm-3.0.180.data/purelib/gm/pb/account_pb2.py
gm-3.0.180.data/purelib/gm/pb/account_pb2.pyi
gm-3.0.180.data/purelib/gm/pb/algo_service_pb2.py
gm-3.0.180.data/purelib/gm/pb/algo_service_pb2.pyi
gm-3.0.180.data/purelib/gm/pb/common_pb2.py
gm-3.0.180.data/purelib/gm/pb/common_pb2.pyi
gm-3.0.180.dist-info/METADATA
gm-3.0.180.dist-info/WHEEL
gm-3.0.180.dist-info/namespace_packages.txt
gm-3.0.180.dist-info/top_level.txt
gm-3.0.180.dist-info/RECORD
