Metadata-Version: 2.1
Name: gm
Version: 3.0.180
Summary: 掘金量化 掘金3 sdk
Home-page: https://www.myquant.cn/
Author: myquant_dev
Author-email: support@myquant.cn
License: Apache 2.0
Classifier: Programming Language :: Python :: 3.6
Classifier: Programming Language :: Python :: 3.7
Classifier: Programming Language :: Python :: 3.8
Classifier: Programming Language :: Python :: 3.9
Classifier: Programming Language :: Python :: 3.10
Classifier: Programming Language :: Python :: 3.11
Classifier: Programming Language :: Python :: 3.12
Classifier: Programming Language :: Python :: 3.13
Requires-Python: >=3.6, <4
Requires-Dist: protobuf (<4.0,>=3.12.2)
Requires-Dist: typing (>=3.6.2)
Requires-Dist: tzdata (<=2023.3)
Requires-Dist: wheel (>=0.37.1)
Requires-Dist: cachetools (==4.2.4) ; python_version < "3.7"
Requires-Dist: pandas (<2.0,>=0.23.0) ; python_version <= "3.11"
Requires-Dist: numpy (<2.0) ; python_version <= "3.11"
Requires-Dist: typing-extensions (>=4.1.1) ; python_version == "3.7.1"
Requires-Dist: pandas (>=0.23.0) ; python_version > "3.11"
Requires-Dist: setuptools (==69.1.1) ; python_version >= "3.12"
Requires-Dist: cachetools (==5.5.0) ; python_version >= "3.7"
Provides-Extra: all
Requires-Dist: scipy (<2,>=1.2.3) ; extra == 'all'
Provides-Extra: scipy
Requires-Dist: scipy (<2,>=1.2.3) ; extra == 'scipy'
